csv_validation-0.0.18.dist-info/METADATA
csv_validation-0.0.18.dist-info/WHEEL
csv_validation-0.0.18.dist-info/licenses/LICENSE
csv_validation/__init__.py
csv_validation/__init__.pyi
csv_validation/csv_validation.cpython-310-i386-linux-gnu.so
csv_validation/py.typed
csv_validation-0.0.18.dist-info/RECORD
