Metadata-Version: 2.4
Name: csv_validation
Version: 0.0.18
Classifier: Programming Language :: Rust
Classifier: Programming Language :: Python :: Implementation :: CPython
Classifier: Programming Language :: Python :: Implementation :: PyPy
License-File: LICENSE
Summary: Blazing fast format validations for your CSV files
Requires-Python: >=3.8
Project-URL: Homepage, https://github.com/charro/csv_validation
